cyseq/__init__.py
cyseq/_seq.cpp
cyseq/_seq.cpython-313-x86_64-linux-gnu.so
cyseq/_seq.pyx
cyseq-0.0.2.dist-info/METADATA
cyseq-0.0.2.dist-info/WHEEL
cyseq-0.0.2.dist-info/top_level.txt
cyseq-0.0.2.dist-info/RECORD
cyseq-0.0.2.dist-info/licenses/AUTHORS.rst
cyseq-0.0.2.dist-info/licenses/CHANGELOG.rst
cyseq-0.0.2.dist-info/licenses/CODE_OF_CONDUCT.rst
cyseq-0.0.2.dist-info/licenses/NOTICE
cyseq-0.0.2.dist-info/licenses/README.rst
cyseq-0.0.2.dist-info/licenses/apache-2.0.LICENSE
