Metadata-Version: 2.4
Name: cyseq
Version: 0.0.2
Summary: "A Cython version of ScanCode-toolkit's licensedcode.seq"
Home-page: https://github.com/aboutcode-org/cyseq
Author: nexB. Inc. and others
Author-email: info@aboutcode.org
License: Apache-2.0
Keywords: utilities
Classifier: Development Status :: 5 - Production/Stable
Classifier: Intended Audience :: Developers
Classifier: Programming Language :: Python :: 3
Classifier: Programming Language :: Python :: 3 :: Only
Classifier: Topic :: Software Development
Classifier: Topic :: Utilities
Requires-Python: >=3.9
License-File: apache-2.0.LICENSE
License-File: NOTICE
License-File: AUTHORS.rst
License-File: CHANGELOG.rst
License-File: CODE_OF_CONDUCT.rst
License-File: README.rst
Provides-Extra: dev
Requires-Dist: pytest>=7.0.1; extra == "dev"
Requires-Dist: pytest-xdist>=2; extra == "dev"
Requires-Dist: aboutcode-toolkit>=7.0.2; extra == "dev"
Requires-Dist: twine; extra == "dev"
Requires-Dist: ruff; extra == "dev"
Requires-Dist: Sphinx>=5.0.2; extra == "dev"
Requires-Dist: sphinx-rtd-theme>=1.0.0; extra == "dev"
Requires-Dist: sphinx-reredirects>=0.1.2; extra == "dev"
Requires-Dist: doc8>=0.11.2; extra == "dev"
Requires-Dist: sphinx-autobuild; extra == "dev"
Requires-Dist: sphinx-rtd-dark-mode>=1.3.0; extra == "dev"
Requires-Dist: sphinx-copybutton; extra == "dev"
Dynamic: license-file
